py_factors/__init__.py
py_factors/factors.py
py_factors-1.0.0.dist-info/LICENSE
py_factors-1.0.0.dist-info/METADATA
py_factors-1.0.0.dist-info/WHEEL
py_factors-1.0.0.dist-info/top_level.txt
py_factors-1.0.0.dist-info/RECORD
