Metadata-Version: 2.1
Name: py-factors
Version: 1.0.0
Summary: python package that gives mathematical factors of a number
Home-page: https://github.com/negeek/py_factors
Author: negeek
Author-email: negeek5ive@gmail.com
License: MIT License
License-File: LICENSE
